RPi/__init__.py
RPi/GPIO/__init__.py
rpi_gpio_emu-0.0.1.dist-info/LICENCE.txt
rpi_gpio_emu-0.0.1.dist-info/METADATA
rpi_gpio_emu-0.0.1.dist-info/WHEEL
rpi_gpio_emu-0.0.1.dist-info/top_level.txt
rpi_gpio_emu-0.0.1.dist-info/RECORD
