Metadata-Version: 2.1
Name: rpi-gpio-emu
Version: 0.0.1
Summary: Placeholder package to emulate RPi.GPIO package on non-Pi devices
Home-page: https://github.com/aharshac/rpi-gpio-emu
Author: Harsha Alva
Author-email: aharshac@gmail.com
License: MIT
Keywords: Raspberry Pi GPIO
Platform: UNKNOWN
Classifier: Development Status :: 5 - Production/Stable
Classifier: Operating System :: POSIX :: Linux
Classifier: License :: OSI Approved :: MIT License
Classifier: Intended Audience :: Developers
Classifier: Programming Language :: Python :: 2.7
Classifier: Programming Language :: Python :: 3
Classifier: Topic :: Software Development
Classifier: Topic :: Home Automation
Classifier: Topic :: System :: Hardware
